Workbook

Sheet Rules
A2: 1 | B2: Banchmark & Universe
B3: a | C3: Banchmark | D3: S&P 500
B4: b | C4: Universe | D4: S&P 300
A5: 2 | B5: Parameter
B6: a | C6: Holding & Review | D6: Monthly
B7: b | C7: Number of stocks | D7: 10-16
B8: c | C8: Weighted Limit | D8: Max 12-15% per stock, sector cap 30%
B9: d | C9: Rebalancing | D9: Monthly
A10: 3 | B10: Data
B11: a | C11: Monthly Price (close) | D11: Min 5-10 years
B12: b | C12: Risk-Free | D12: T-Bill 3 Month

Sheet Summary
A1: No | B1: Date | C1: Balance | D1: % Change
A2: 1 | B2: 45292 | C2: ='2024'!H114 -> 9799 | D2: 0
A3: 2 | B3: 45323 | C3: ='2024'!J114 -> 10166.629 | D3: =(C3-C2)/C2 -> 0.037517009
A4: 3 | B4: 45352 | C4: ='2024'!L114 -> 10812.168 | D4: =(C4-C3)/C3 -> 0.063495814
A5: 4 | B5: 45383 | C5: ='2024'!N114 -> 10970.92 | D5: =(C5-C4)/C4 -> 0.014682727
A6: 5 | B6: 45413 | C6: ='2024'!P114 -> 10264.146 | D6: =(C6-C5)/C5 -> -0.06442245
A7: 6 | B7: 45444 | C7: ='2024'!R114 -> 10967.639 | D7: =(C7-C6)/C6 -> 0.068538818
A8: 7 | B8: 45474 | C8: ='2024'!T114 -> 11410.858 | D8: =(C8-C7)/C7 -> 0.040411523
A9: 8 | B9: 45505 | C9: ='2024'!V114 -> 10835.091 | D9: =(C9-C8)/C8 -> -0.050457799
A10: 9 | B10: 45536 | C10: ='2024'!X114 -> 11720.464 | D10: =(C10-C9)/C9 -> 0.081713459
A11: 10 | B11: 45566 | C11: ='2024'!Z114 -> 11947.281 | D11: =(C11-C10)/C10 -> 0.019352291
A12: 11 | B12: 45597 | C12: ='2024'!AB114 -> 11701.669 | D12: =(C12-C11)/C11 -> -0.020558027
A13: 12 | B13: 45627 | C13: ='2024'!AD114 -> 12497.176 | D13: =(C13-C12)/C12 -> 0.067982381
C15: Annual Return | D15: =(C13-C2)/C2 -> 0.27535219
C16: Average | D16: =AVERAGE(D2:D13) -> 0.021521312
C17: Volatility | D17: ='2024'!H118 -> 0.045205784

Sheet Universe
A1: No | B1: Index | C1: Ticker | D1: Company | E1: Sector | F1: Market Cap (B)
A2: 1 | B2: S&P 500 | C2: NVDA | D2: NVIDIA Corporation | E2: Information Technology | F2: 4150
A3: 2 | B3: S&P 500 | C3: AAPL | D3: Apple Inc. | E3: Information Technology | F3: 4020
A4: 3 | B4: S&P 500 | C4: GOOG | D4: Alphabet Inc. | E4: Information Technology | F4: 3710
A5: 4 | B5: S&P 500 | C5: GOOGL | D5: Alphabet Inc. | E5: Information Technology | F5: 3580
A6: 5 | B6: S&P 500 | C6: MSFT | D6: Microsoft Corporation | E6: Information Technology | F6: 3540
A7: 6 | B7: S&P 500 | C7: AMZN | D7: Amazon.com Inc. | E7: Consumer Discretionary | F7: 2370
A8: 7 | B8: S&P 500 | C8: META | D8: Meta Platforms Inc. | E8: Information Technology | F8: 1640
A9: 8 | B9: S&P 500 | C9: TSLA | D9: Tesla Inc. | E9: Consumer Discretionary | F9: 1550
A10: 9 | B10: S&P 500 | C10: AVGO | D10: Broadcom Inc. | E10: Information Technology | F10: 1540
A11: 10 | B11: S&P 500 | C11: BRK.B | D11: Berkshire Hathaway Inc. | E11: Financials | F11: 1090
A12: 11 | B12: S&P 500 | C12: LLY | D12: Eli Lilly and Company | E12: Health Care | F12: 933
A13: 12 | B13: S&P 500 | C13: WMT | D13: Walmart Inc. | E13: Consumer Staples | F13: 922
... A201: 200 | B201: S&P 500 | C201: RCL | D201: Royal Caribbean | E201: Consumer Discretionary | F201: 24

Sheet 2024
A1: Balance | B1: 10000
A2: No | B2: Sector | C2: Ticker | D2: Company | E2: Div % | F2: Number of Stock | G2: Price Buy | H2: January (1) | I2: Price Feb | J2: February (2) | K2: Price Mar | L2: March (3) | M2: Price Apr | N2: April (4) | O2: Price May | P2: May (5) | Q2: Price Jun | R2: June (6) | S2: Price Jul | T2: July (7) | U2: Price Aug | V2: August (8) | W2: Price Sep | X2: September (9) | Y2: Price Oct | Z2: Oktober (10) | AA2: Price Nov | AB2: November (11) | AC2: Price Dec | AD2: Desember (12)
A3: ROUND 1
A4: 1 | B4: =VLOOKUP(C4,Universe!$C$2:$E$201,3,FALSE) -> Information Technology | C4: INTC | D4: =VLOOKUP(C4,Universe!$C$2:$D$201,2,FALSE) -> Intel Corp. | E4: 0.15 | F4: =($B$1*E4)/G4 -> 30.248034 | G4: 49.59 | H4: =F4*G4 -> 1500 | I4: 42.79 | J4: =F4*I4 -> 1294.3134 | K4: 43.37 | L4: =F4*K4 -> 1311.8572
A5: 2 | B5: =VLOOKUP(C5,Universe!$C$2:$E$201,3,FALSE) -> Health Care | C5: LLY | D5: =VLOOKUP(C5,Universe!$C$2:$D$201,2,FALSE) -> Eli Lilly and Company | E5: 0.15 | F5: =($B$1*E5)/G5 -> 2.6093764 | G5: 574.85 | H5: =F5*G5 -> 1500 | I5: 651.29 | J5: =F5*I5 -> 1699.4607 | K5: 772.65 | L5: =F5*K5 -> 2016.1346
A6: 3 | B6: =VLOOKUP(C6,Universe!$C$2:$E$201,3,FALSE) -> Consumer Discretionary | C6: BKNG | D6: =VLOOKUP(C6,Universe!$C$2:$D$201,2,FALSE) -> Booking Holdings | E6: 0.15 | F6: =($B$1*E6)/G6 -> 0.42978588 | G6: 3490.11 | H6: =F6*G6 -> 1500 | I6: 3501.16 | J6: =F6*I6 -> 1504.7491 | K6: 3443.39 | L6: =F6*K6 -> 1479.9204
A7: 4 | B7: =VLOOKUP(C7,Universe!$C$2:$E$201,3,FALSE) -> Consumer Discretionary | C7: AMZN | D7: =VLOOKUP(C7,Universe!$C$2:$D$201,2,FALSE) -> Amazon.com Inc. | E7: 0.1 | F7: =($B$1*E7)/G7 -> 6.5815453 | G7: 151.94 | H7: =F7*G7 -> 1000 | I7: 159.28 | J7: =F7*I7 -> 1048.3085 | K7: 178.22 | L7: =F7*K7 -> 1172.963
A8: 5 | B8: =VLOOKUP(C8,Universe!$C$2:$E$201,3,FALSE) -> Information Technology | C8: WDAY | D8: =VLOOKUP(C8,Universe!$C$2:$D$201,2,FALSE) -> Workday Inc. | E8: 0.1083 | F8: =($B$1*E8)/G8 -> 3.9230602 | G8: 276.06 | H8: =F8*G8 -> 1083 | I8: 294 | J8: =F8*I8 -> 1153.3797 | K8: 291.92 | L8: =F8*K8 -> 1145.2197
A9: 6 | B9: =VLOOKUP(C9,Universe!$C$2:$E$201,3,FALSE) -> Information Technology | C9: STX | D9: =VLOOKUP(C9,Universe!$C$2:$D$201,2,FALSE) -> Seagate Tech. | E9: 0.0694 | F9: =($B$1*E9)/G9 -> 8.506987 | G9: 81.58 | H9: =F9*G9 -> 694 | I9: 82.94 | J9: =F9*I9 -> 705.5695 | K9: 92.84 | L9: =F9*K9 -> 789.78867
A10: 7 | B10: =VLOOKUP(C10,Universe!$C$2:$E$201,3,FALSE) -> Information Technology | C10: TEAM | D10: =VLOOKUP(C10,Universe!$C$2:$D$201,2,FALSE) -> Atlassian Corp. | E10: 0.0969 | F10: =($B$1*E10)/G10 -> 4.0738249 | G10: 237.86 | H10: =F10*G10 -> 969 | I10: 254.9 | J10: =F10*I10 -> 1038.418 | K10: 209.2 | L10: =F10*K10 -> 852.24418
A11: 8 | B11: =VLOOKUP(C11,Universe!$C$2:$E$201,3,FALSE) -> Information Technology | C11: META | D11: =VLOOKUP(C11,Universe!$C$2:$D$201,2,FALSE) -> Meta Platforms Inc. | E11: 0.0654 | F11: =($B$1*E11)/G11 -> 1.8605974 | G11: 351.5 | H11: =F11*G11 -> 654 | I11: 392.04 | J11: =F11*I11 -> 729.42862 | K11: 499.34 | L11: =F11*K11 -> 929.07073
A12: 9 | B12: =VLOOKUP(C12,Universe!$C$2:$E$201,3,FALSE) -> Consumer Discretionary | C12: NFLX | D12: =VLOOKUP(C12,Universe!$C$2:$D$201,2,FALSE) -> Netflix Inc. | E12: 0.0293 | F12: =($B$1*E12)/G12 -> 6.0176628 | G12: 48.69 | H12: =F12*G12 -> 293 | I12: 56.75 | J12: =F12*I12 -> 341.50236 | K12: 61.93 | L12: =F12*K12 -> 372.67386
A13: 10 | B13: =VLOOKUP(C13,Universe!$C$2:$E$201,3,FALSE) -> Industrials | C13: GE | D13: =VLOOKUP(C13,Universe!$C$2:$D$201,2,FALSE) -> GE Aerospace | E13: 0.027 | F13: =($B$1*E13)/G13 -> 2.6804328 | G13: 100.73 | H13: =F13*G13 -> 270 | I13: 106.87 | J13: =F13*I13 -> 286.45786 | K13: 125.22 | L13: =F13*K13 -> 335.6438
A14: 11 | B14: =VLOOKUP(C14,Universe!$C$2:$E$201,3,FALSE) -> Information Technology | C14: CRM | D14: =VLOOKUP(C14,Universe!$C$2:$D$201,2,FALSE) -> Salesforce Inc. | E14: 0.0204 | F14: =($B$1*E14)/G14 -> 0.78341014 | G14: 260.4 | H14: =F14*G14 -> 204 | I14: 280.85 | J14: =F14*I14 -> 220.02074 | K14: 313.58 | L14: =F14*K14 -> 245.66175
A15: 12 | B15: =VLOOKUP(C15,Universe!$C$2:$E$201,3,FALSE) -> Industrials | C15: ETN | D15: =VLOOKUP(C15,Universe!$C$2:$D$201,2,FALSE) -> Eaton Corp | E15: 0.0132 | F15: =($B$1*E15)/G15 -> 0.56050955 | G15: 235.5 | H15: =F15*G15 -> 132 | I15: 258.73 | J15: =F15*I15 -> 145.02064 | K15: 287.22 | L15: =F15*K15 -> 160.98955
F16: Total | H16: =SUM(H4:H15) -> 9799 | J16: =SUM(J4:J15) -> 10166.629 | L16: =SUM(L4:L15) -> 10812.168
J17: =(J16-H16)/H16 -> 0.037517009 | L17: =(L16-J16)/J16 -> 0.063495814
A19: ROUND 2 | D19: =SUM(L4:L15) -> 10812.168
A20: 1 | B20: =VLOOKUP(C20,Universe!$C$2:$E$201,3,FALSE) -> Consumer Discretionary | C20: AMZN | D20: =VLOOKUP(C20,Universe!$C$2:$D$201,2,FALSE) -> Amazon.com Inc. | E20: 0.15 | F20: =($D$19*E20)/K20 -> 9.1001298 | K20: 178.22 | L20: =F20*K20 -> 1621.8251 | M20: 180.97 | N20: =F20*M20 -> 1646.8505
A21: 2 | B21: =VLOOKUP(C21,Universe!$C$2:$E$201,3,FALSE) -> Consumer Staples | C21: COST | D21: =VLOOKUP(C21,Universe!$C$2:$D$201,2,FALSE) -> Costco Wholesale Corp | E21: 0.15 | F21: =($D$19*E21)/K21 -> 2.1848354 | K21: 742.31 | L21: =F21*K21 -> 1621.8251 | M21: 714.38 | N21: =F21*M21 -> 1560.8027
A22: 3 | B22: =VLOOKUP(C22,Universe!$C$2:$E$201,3,FALSE) -> Information Technology | C22: INTC | D22: =VLOOKUP(C22,Universe!$C$2:$D$201,2,FALSE) -> Intel Corp. | E22: 0.15 | F22: =($D$19*E22)/K22 -> 37.395092 | K22: 43.37 | L22: =F22*K22 -> 1621.8251 | M22: 44.06 | N22: =F22*M22 -> 1647.6277
A23: 4 | B23: =VLOOKUP(C23,Universe!$C$2:$E$201,3,FALSE) -> Health Care | C23: VRTX | D23: =VLOOKUP(C23,Universe!$C$2:$D$201,2,FALSE) -> Vertex Pharma | E23: 0.15 | F23: =($D$19*E23)/K23 -> 3.7476318 | K23: 432.76 | L23: =F23*K23 -> 1621.8251 | M23: 420.48 | N23: =F23*M23 -> 1575.8042
A24: 5 | B24: =VLOOKUP(C24,Universe!$C$2:$E$201,3,FALSE) -> Financials | C24: PGR | D24: =VLOOKUP(C24,Universe!$C$2:$D$201,2,FALSE) -> Progressive Corp | E24: 0.15 | F24: =($D$19*E24)/K24 -> 8.8228981 | K24: 183.82 | L24: =F24*K24 -> 1621.8251 | M24: 205.47 | N24: =F24*M24 -> 1812.8409
A25: 6 | B25: =VLOOKUP(C25,Universe!$C$2:$E$201,3,FALSE) -> Industrials | C25: GE | D25: =VLOOKUP(C25,Universe!$C$2:$D$201,2,FALSE) -> GE Aerospace | E25: 0.0657 | F25: =($D$19*E25)/K25 -> 5.672891 | K25: 125.22 | L25: =F25*K25 -> 710.35941 | M25: 138.41 | N25: =F25*M25 -> 785.18484
A26: 7 | B26: =VLOOKUP(C26,Universe!$C$2:$E$201,3,FALSE) -> Information Technology | C26: META | D26: =VLOOKUP(C26,Universe!$C$2:$D$201,2,FALSE) -> Meta Platforms Inc. | E26: 0.0493 | F26: =($D$19*E26)/K26 -> 1.0674888 | K26: 499.34 | L26: =F26*K26 -> 533.03986 | M26: 488.46 | N26: =F26*M26 -> 521.42558
A27: 8 | B27: =VLOOKUP(C27,Universe!$C$2:$E$201,3,FALSE) -> Health Care | C27: LLY | D27: =VLOOKUP(C27,Universe!$C$2:$D$201,2,FALSE) -> Eli Lilly and Company | E27: 0.0479 | F27: =($D$19*E27)/K27 -> 0.67029422 | K27: 772.65 | L27: =F27*K27 -> 517.90283 | M27: 751.34 | N27: =F27*M27 -> 503.61886
A28: 9 | B28: =VLOOKUP(C28,Universe!$C$2:$E$201,3,FALSE) -> Information Technology | C28: CRM | D28: =VLOOKUP(C28,Universe!$C$2:$D$201,2,FALSE) -> Salesforce Inc. | E28: 0.0303 | F28: =($D$19*E28)/K28 -> 1.0447372 | K28: 313.58 | L28: =F28*K28 -> 327.60868 | M28: 299.5 | N28: =F28*M28 -> 312.89878
A29: 10 | B29: =VLOOKUP(C29,Universe!$C$2:$E$201,3,FALSE) -> Consumer Discretionary | C29: NFLX | D29: =VLOOKUP(C29,Universe!$C$2:$D$201,2,FALSE) -> Netflix Inc. | E29: 0.0276 | F29: =($D$19*E29)/K29 -> 4.8185988 | K29: 61.93 | L29: =F29*K29 -> 298.41582 | M29: 61.43 | N29: =F29*M29 -> 296.00653
A30: 11 | B30: =VLOOKUP(C30,Universe!$C$2:$E$201,3,FALSE) -> Information Technology | C30: UBER | D30: =VLOOKUP(C30,Universe!$C$2:$D$201,2,FALSE) -> Uber Technologies | E30: 0.0198 | F30: =($D$19*E30)/K30 -> 2.6419958 | K30: 81.03 | L30: =F30*K30 -> 214.08092 | M30: 76.4 | N30: =F30*M30 -> 201.84848
A31: 12 | B31: =VLOOKUP(C31,Universe!$C$2:$E$201,3,FALSE) -> Industrials | C31: ETN | D31: =VLOOKUP(C31,Universe!$C$2:$D$201,2,FALSE) -> Eaton Corp | E31: 0.0092 | F31: =($D$19*E31)/K31 -> 0.34632665 | K31: 287.22 | L31: =F31*K31 -> 99.471942 | M31: 306.1 | N31: =F31*M31 -> 106.01059
L32: =SUM(L20:L31) -> 10810.005 | N32: =SUM(N20:N31) -> 10970.92
N33: =(N32-L32)/L32 -> 0.014885704
A35: ROUND 3 | D35: =N32 -> 10970.92
A36: 1 | B36: =VLOOKUP(C36,Universe!$C$2:$E$201,3,FALSE) -> Financials | C36: AIG | D36: =VLOOKUP(C36,Universe!$C$2:$D$201,2,FALSE) -> AIG | E36: 0.15 | F36: =($D$19*E36)/M36 -> 21.687953 | M36: 74.78 | N36: =F36*M36 -> 1621.8251 | O36: 73.01 | P36: =F36*O36 -> 1583.4375
A37: 2 | B37: =VLOOKUP(C37,Universe!$C$2:$E$201,3,FALSE) -> Health Care | C37: CI | D37: =VLOOKUP(C37,Universe!$C$2:$D$201,2,FALSE) -> The Cigna Group | E37: 0.15 | F37: =($D$19*E37)/M37 -> 4.6017056 | M37: 352.44 | N37: =F37*M37 -> 1621.8251 | O37: 345.76 | P37: =F37*O37 -> 1591.0857
A38: 3 | B38: =VLOOKUP(C38,Universe!$C$2:$E$201,3,FALSE) -> Financials | C38: PGR | D38: =VLOOKUP(C38,Universe!$C$2:$D$201,2,FALSE) -> Progressive Corp | E38: 0.15 | F38: =($D$19*E38)/M38 -> 7.8932454 | M38: 205.47 | N38: =F38*M38 -> 1621.8251 | O38: 207.38 | P38: =F38*O38 -> 1636.9012
A39: 4 | B39: =VLOOKUP(C39,Universe!$C$2:$E$201,3,FALSE) -> Consumer Discretionary | C39: NFLX | D39: =VLOOKUP(C39,Universe!$C$2:$D$201,2,FALSE) -> Netflix Inc. | E39: 0.15 | F39: =($D$19*E39)/M39 -> 26.401191 | M39: 61.43 | N39: =F39*M39 -> 1621.8251 | O39: 55.17 | P39: =F39*O39 -> 1456.5537
A40: 5 | B40: =VLOOKUP(C40,Universe!$C$2:$E$201,3,FALSE) -> Information Technology | C40: IBM | D40: =VLOOKUP(C40,Universe!$C$2:$D$201,2,FALSE) -> IBM Corporation | E40: 0.15 | F40: =($D$19*E40)/M40 -> 8.9991407 | M40: 180.22 | N40: =F40*M40 -> 1621.8251 | O40: 156.11 | P40: =F40*O40 -> 1404.8559
A41: 6 | B41: =VLOOKUP(C41,Universe!$C$2:$E$201,3,FALSE) -> Consumer Discretionary | C41: AMZN | D41: =VLOOKUP(C41,Universe!$C$2:$D$201,2,FALSE) -> Amazon.com Inc. | E41: 0.15 | F41: =($D$19*E41)/M41 -> 8.9618452 | M41: 180.97 | N41: =F41*M41 -> 1621.8251 | O41: 179 | P41: =F41*O41 -> 1604.1703
A42: 7 | B42: =VLOOKUP(C42,Universe!$C$2:$E$201,3,FALSE) -> Information Technology | C42: META | D42: =VLOOKUP(C42,Universe!$C$2:$D$201,2,FALSE) -> Meta Platforms Inc. | E42: 0.0514 | F42: =($D$19*E42)/M42 -> 1.1377501 | M42: 488.46 | N42: =F42*M42 -> 555.74541 | O42: 436.61 | P42: =F42*O42 -> 496.75307
A43: 8 | B43: =VLOOKUP(C43,Universe!$C$2:$E$201,3,FALSE) -> Information Technology | C43: UBER | D43: =VLOOKUP(C43,Universe!$C$2:$D$201,2,FALSE) -> Uber Technologies | E43: 0.0293 | F43: =($D$19*E43)/M43 -> 4.1465512 | M43: 76.4 | N43: =F43*M43 -> 316.79651 | O43: 67.79 | P43: =F43*O43 -> 281.0947
A44: 9 | B44: =VLOOKUP(C44,Universe!$C$2:$E$201,3,FALSE) -> Consumer Staples | C44: COST | D44: =VLOOKUP(C44,Universe!$C$2:$D$201,2,FALSE) -> Costco Wholesale Corp | E44: 0.0193 | F44: =($D$19*E44)/M44 -> 0.29210621 | M44: 714.38 | N44: =F44*M44 -> 208.67483 | O44: 716.5 | P44: =F44*O44 -> 209.2941
N45: =SUM(N36:N44) -> 10812.168 | P45: =SUM(P36:P44) -> 10264.146
P46: =(P45-N45)/N45 -> -0.050685621
A48: ROUND 4 | D48: =P45 -> 10264.146
A49: 1 | B49: =VLOOKUP(C49,Universe!$C$2:$E$201,3,FALSE) -> Consumer Discretionary | C49: AMZN | D49: =VLOOKUP(C49,Universe!$C$2:$D$201,2,FALSE) -> Amazon.com Inc. | E49: 0.15 | F49: =$D$48*E49/O49 -> 8.6012398 | O49: 179 | P49: =F49*O49 -> 1539.6219 | Q49: 176.44 | R49: =F49*Q49 -> 1517.6027 | S49: 197.2 | T49: =F49*S49 -> 1696.1645
A50: 2 | B50: =VLOOKUP(C50,Universe!$C$2:$E$201,3,FALSE) -> Health Care | C50: CI | D50: =VLOOKUP(C50,Universe!$C$2:$D$201,2,FALSE) -> The Cigna Group | E50: 0.15 | F50: =$D$48*E50/O50 -> 4.452863 | O50: 345.76 | P50: =F50*O50 -> 1539.6219 | Q50: 333.61 | R50: =F50*Q50 -> 1485.5196 | S50: 317.14 | T50: =F50*S50 -> 1412.181
A51: 3 | B51: =VLOOKUP(C51,Universe!$C$2:$E$201,3,FALSE) -> Information Technology | C51: NTAP | D51: =VLOOKUP(C51,Universe!$C$2:$D$201,2,FALSE) -> NetApp Inc. | E51: 0.15 | F51: =$D$48*E51/O51 -> 15.683222 | O51: 98.17 | P51: =F51*O51 -> 1539.6219 | Q51: 117.07 | R51: =F51*Q51 -> 1836.0348 | S51: 126.6 | T51: =F51*S51 -> 1985.4959
A52: 4 | B52: =VLOOKUP(C52,Universe!$C$2:$E$201,3,FALSE) -> Consumer Discretionary | C52: NFLX | D52: =VLOOKUP(C52,Universe!$C$2:$D$201,2,FALSE) -> Netflix Inc. | E52: 0.15 | F52: =$D$48*E52/O52 -> 27.906868 | O52: 55.17 | P52: =F52*O52 -> 1539.6219 | Q52: 64.16 | R52: =F52*Q52 -> 1790.5047 | S52: 67.36 | T52: =F52*S52 -> 1879.8066
A53: 5 | B53: =VLOOKUP(C53,Universe!$C$2:$E$201,3,FALSE) -> Financials | C53: PGR | D53: =VLOOKUP(C53,Universe!$C$2:$D$201,2,FALSE) -> Progressive Corp | E53: 0.15 | F53: =$D$48*E53/O53 -> 7.4241582 | O53: 207.38 | P53: =F53*O53 -> 1539.6219 | Q53: 206.77 | R53: =F53*Q53 -> 1535.0932 | S53: 205.09 | T53: =F53*S53 -> 1522.6206
A54: 6 | B54: =VLOOKUP(C54,Universe!$C$2:$E$201,3,FALSE) -> Information Technology | C54: APH | D54: =VLOOKUP(C54,Universe!$C$2:$D$201,2,FALSE) -> Amphenol Corp | E54: 0.1282 | F54: =$D$48*E54/O54 -> 22.378632 | O54: 58.8 | P54: =F54*O54 -> 1315.8635 | Q54: 65.26 | R54: =F54*Q54 -> 1460.4295 | S54: 66.68 | T54: =F54*S54 -> 1492.2072
A55: 7 | B55: =VLOOKUP(C55,Universe!$C$2:$E$201,3,FALSE) -> Consumer Discretionary | C55: RCL | D55: =VLOOKUP(C55,Universe!$C$2:$D$201,2,FALSE) -> Royal Caribbean | E55: 0.1218 | F55: =$D$48*E55/O55 -> 9.218885 | O55: 135.61 | P55: =F55*O55 -> 1250.173 | Q55: 145.62 | R55: =F55*Q55 -> 1342.454 | S55: 154.29 | T55: =F55*S55 -> 1422.3818
P56: =SUM(P49:P55) -> 10264.146 | R56: =SUM(R49:R55) -> 10967.639 | T56: =SUM(T49:T55) -> 11410.858
R57: =(R56-P56)/P56 -> 0.068538818 | T57: =(T56-R56)/R56 -> 0.040411523
A59: ROUND 5 | D59: =T56 -> 11410.858
A60: 1 | B60: =VLOOKUP(C60,Universe!$C$2:$E$201,3,FALSE) -> Consumer Discretionary | C60: AMZN | D60: =VLOOKUP(C60,Universe!$C$2:$D$201,2,FALSE) -> Amazon.com Inc. | E60: 0.15 | F60: =$D$59*E60/S60 -> 8.6796584 | S60: 197.2 | T60: =F60*S60 -> 1711.6286 | U60: 184.07 | V60: =F60*U60 -> 1597.6647
A61: 2 | B61: =VLOOKUP(C61,Universe!$C$2:$E$201,3,FALSE) -> Consumer Discretionary | C61: NFLX | D61: =VLOOKUP(C61,Universe!$C$2:$D$201,2,FALSE) -> Netflix Inc. | E61: 0.15 | F61: =$D$59*E61/S61 -> 25.410164 | S61: 67.36 | T61: =F61*S61 -> 1711.6286 | U61: 62.49 | V61: =F61*U61 -> 1587.8811
A62: 3 | B62: =VLOOKUP(C62,Universe!$C$2:$E$201,3,FALSE) -> Financials | C62: PGR | D62: =VLOOKUP(C62,Universe!$C$2:$D$201,2,FALSE) -> Progressive Corp | E62: 0.15 | F62: =$D$59*E62/S62 -> 8.345744 | S62: 205.09 | T62: =F62*S62 -> 1711.6286 | U62: 210.89 | V62: =F62*U62 -> 1760.0339
A63: 4 | B63: =VLOOKUP(C63,Universe!$C$2:$E$201,3,FALSE) -> Consumer Staples | C63: COST | D63: =VLOOKUP(C63,Universe!$C$2:$D$201,2,FALSE) -> Costco Wholesale Corp | E63: 0.15 | F63: =$D$59*E63/S63 -> 2.0401548 | S63: 838.97 | T63: =F63*S63 -> 1711.6286 | U63: 811.57 | V63: =F63*U63 -> 1655.7284
A64: 5 | B64: =VLOOKUP(C64,Universe!$C$2:$E$201,3,FALSE) -> Consumer Discretionary | C64: RCL | D64: =VLOOKUP(C64,Universe!$C$2:$D$201,2,FALSE) -> Royal Caribbean | E64: 0.139 | F64: =$D$59*E64/S64 -> 10.280052 | S64: 154.29 | T64: =F64*S64 -> 1586.1092 | U64: 146.03 | V64: =F64*U64 -> 1501.196
A65: 6 | B65: =VLOOKUP(C65,Universe!$C$2:$E$201,3,FALSE) -> Information Technology | C65: UBER | D65: =VLOOKUP(C65,Universe!$C$2:$D$201,2,FALSE) -> Uber Technologies | E65: 0.1331 | F65: =$D$59*E65/S65 -> 21.361254 | S65: 71.1 | T65: =F65*S65 -> 1518.7851 | U65: 61.02 | V65: =F65*U65 -> 1303.4637
A66: 7 | B66: =VLOOKUP(C66,Universe!$C$2:$E$201,3,FALSE) -> Information Technology | C66: META | D66: =VLOOKUP(C66,Universe!$C$2:$D$201,2,FALSE) -> Meta Platforms Inc. | E66: 0.1237 | F66: =$D$59*E66/S66 -> 2.8106232 | S66: 502.21 | T66: =F66*S66 -> 1411.5231 | U66: 495.3 | V66: =F66*U66 -> 1392.1017
A67: 8 | B67: =VLOOKUP(C67,Universe!$C$2:$E$201,3,FALSE) -> Information Technology | C67: MU | D67: =VLOOKUP(C67,Universe!$C$2:$D$201,2,FALSE) -> Micron Technology | E67: 0.0042 | F67: =$D$59*E67/S67 -> 0.36665597 | S67: 130.71 | T67: =F67*S67 -> 47.925602 | U67: 100.97 | V67: =F67*U67 -> 37.021253
T68: =SUM(T60:T67) -> 11410.858 | V68: =SUM(V60:V67) -> 10835.091
V69: =(V68-T68)/T68 -> -0.050457799
A71: ROUND 6 | D71: =V68 -> 10835.091
A72: 1 | B72: =VLOOKUP(C72,Universe!$C$2:$E$201,3,FALSE) -> Consumer Staples | C72: COST | D72: =VLOOKUP(C72,Universe!$C$2:$D$201,2,FALSE) -> Costco Wholesale Corp | E72: 0.15 | F72: =$D$71*E72/U72 -> 2.0026167 | U72: 811.57 | V72: =F72*U72 -> 1625.2636 | W72: 886.57 | X72: =F72*W72 -> 1775.4599
A73: 2 | B73: =VLOOKUP(C73,Universe!$C$2:$E$201,3,FALSE) -> Consumer Staples | C73: CL | D73: =VLOOKUP(C73,Universe!$C$2:$D$201,2,FALSE) -> Colgate-Palmolive | E73: 0.15 | F73: =$D$71*E73/U73 -> 16.574175 | U73: 98.06 | V73: =F73*U73 -> 1625.2636 | W73: 103.47 | X73: =F73*W73 -> 1714.9299
A74: 3 | B74: =VLOOKUP(C74,Universe!$C$2:$E$201,3,FALSE) -> Information Technology | C74: TMUS | D74: =VLOOKUP(C74,Universe!$C$2:$D$201,2,FALSE) -> T-Mobile US | E74: 0.15 | F74: =$D$71*E74/U74 -> 8.8841348 | U74: 182.94 | V74: =F74*U74 -> 1625.2636 | W74: 194.96 | X74: =F74*W74 -> 1732.0509
A75: 4 | B75: =VLOOKUP(C75,Universe!$C$2:$E$201,3,FALSE) -> Financials | C75: PGR | D75: =VLOOKUP(C75,Universe!$C$2:$D$201,2,FALSE) -> Progressive Corp | E75: 0.15 | F75: =$D$71*E75/U75 -> 7.7066889 | U75: 210.89 | V75: =F75*U75 -> 1625.2636 | W75: 247.06 | X75: =F75*W75 -> 1904.0146
A76: 5 | B76: =VLOOKUP(C76,Universe!$C$2:$E$201,3,FALSE) -> Health Care | C76: BSX | D76: =VLOOKUP(C76,Universe!$C$2:$D$201,2,FALSE) -> Boston Scientific | E76: 0.1442 | F76: =$D$71*E76/U76 -> 20.78792 | U76: 75.16 | V76: =F76*U76 -> 1562.4201 | W76: 81.79 | X76: =F76*W76 -> 1700.244
A77: 6 | B77: =VLOOKUP(C77,Universe!$C$2:$E$201,3,FALSE) -> Communication Services | C77: T | D77: =VLOOKUP(C77,Universe!$C$2:$D$201,2,FALSE) -> AT&T Inc. | E77: 0.0963 | F77: =$D$71*E77/U77 -> 56.707568 | U77: 18.4 | V77: =F77*U77 -> 1043.4192 | W77: 18.81 | X77: =F77*W77 -> 1066.6693
A78: 7 | B78: =VLOOKUP(C78,Universe!$C$2:$E$201,3,FALSE) -> Health Care | C78: CI | D78: =VLOOKUP(C78,Universe!$C$2:$D$201,2,FALSE) -> The Cigna Group | E78: 0.0733 | F78: =$D$71*E78/U78 -> 2.4565795 | U78: 323.3 | V78: =F78*U78 -> 794.21216 | W78: 351.69 | X78: =F78*W78 -> 863.95445
A79: 8 | B79: =VLOOKUP(C79,Universe!$C$2:$E$201,3,FALSE) -> Financials | C79: CB | D79: =VLOOKUP(C79,Universe!$C$2:$D$201,2,FALSE) -> Chubb Ltd | E79: 0.0505 | F79: =$D$71*E79/U79 -> 2.0383404 | U79: 268.44 | V79: =F79*U79 -> 547.17209 | W79: 280.51 | X79: =F79*W79 -> 571.77485
A80: 9 | B80: =VLOOKUP(C80,Universe!$C$2:$E$201,3,FALSE) -> Industrials | C80: GD | D80: =VLOOKUP(C80,Universe!$C$2:$D$201,2,FALSE) -> General Dynamics | E80: 0.0222 | F80: =$D$71*E80/U80 -> 0.84057526 | U80: 286.16 | V80: =F80*U80 -> 240.53902 | W80: 291.93 | X80: =F80*W80 -> 245.38913
A81: 10 | B81: =VLOOKUP(C81,Universe!$C$2:$E$201,3,FALSE) -> Information Technology | C81: STX | D81: =VLOOKUP(C81,Universe!$C$2:$D$201,2,FALSE) -> Seagate Tech. | E81: 0.0134 | F81: =$D$71*E81/U81 -> 1.5120831 | U81: 96.02 | V81: =F81*U81 -> 145.19022 | W81: 96.54 | X81: =F81*W81 -> 145.9765
V82: =SUM(V72:V81) -> 10834.007 | X82: =SUM(X72:X81) -> 11720.464
X83: =(X82-V82)/V82 -> 0.081821641
A85: ROUND 7 | D85: =X82 -> 11720.464
A86: 1 | B86: =VLOOKUP(C86,Universe!$C$2:$E$201,3,FALSE) -> Consumer Staples | C86: CL | D86: =VLOOKUP(C86,Universe!$C$2:$D$201,2,FALSE) -> Colgate-Palmolive | E86: 0.15 | F86: =$D$85*E86/W86 -> 16.991104 | W86: 103.47 | X86: =F86*W86 -> 1758.0695 | Y86: 99.42 | Z86: =F86*Y86 -> 1689.2556 | AA86: 91.13 | AB86: =F86*AA86 -> 1548.3993
A87: 2 | B87: =VLOOKUP(C87,Universe!$C$2:$E$201,3,FALSE) -> Industrials | C87: NOC | D87: =VLOOKUP(C87,Universe!$C$2:$D$201,2,FALSE) -> Northrop Grumman | E87: 0.15 | F87: =$D$85*E87/W87 -> 3.4465194 | W87: 510.1 | X87: =F87*W87 -> 1758.0695 | Y87: 532.35 | Z87: =F87*Y87 -> 1834.7546 | AA87: 496.2 | AB87: =F87*AA87 -> 1710.1629
A88: 3 | B88: =VLOOKUP(C88,Universe!$C$2:$E$201,3,FALSE) -> Consumer Staples | C88: WMT | D88: =VLOOKUP(C88,Universe!$C$2:$D$201,2,FALSE) -> Walmart Inc. | E88: 0.15 | F88: =$D$85*E88/W88 -> 23.032484 | W88: 76.33 | X88: =F88*W88 -> 1758.0695 | Y88: 80.32 | Z88: =F88*Y88 -> 1849.9691 | AA88: 81.23 | AB88: =F88*AA88 -> 1870.9287
A89: 4 | B89: =VLOOKUP(C89,Universe!$C$2:$E$201,3,FALSE) -> Communication Services | C89: T | D89: =VLOOKUP(C89,Universe!$C$2:$D$201,2,FALSE) -> AT&T Inc. | E89: 0.1198 | F89: =$D$85*E89/W89 -> 74.647078 | W89: 18.81 | X89: =F89*W89 -> 1404.1115 | Y89: 20.91 | Z89: =F89*Y89 -> 1560.8704 | AA89: 21.17 | AB89: =F89*AA89 -> 1580.2786
A90: 5 | B90: =VLOOKUP(C90,Universe!$C$2:$E$201,3,FALSE) -> Information Technology | C90: TMUS | D90: =VLOOKUP(C90,Universe!$C$2:$D$201,2,FALSE) -> T-Mobile US | E90: 0.0873 | F90: =$D$85*E90/W90 -> 5.2482379 | W90: 194.96 | X90: =F90*W90 -> 1023.1965 | Y90: 202.2 | Z90: =F90*Y90 -> 1061.1937 | AA90: 219.06 | AB90: =F90*AA90 -> 1149.679
A91: 6 | B91: =VLOOKUP(C91,Universe!$C$2:$E$201,3,FALSE) -> Consumer Staples | C91: COST | D91: =VLOOKUP(C91,Universe!$C$2:$D$201,2,FALSE) -> Costco Wholesale Corp | E91: 0.0693 | F91: =$D$85*E91/W91 -> 0.91614664 | W91: 886.57 | X91: =F91*W91 -> 812.22812 | Y91: 871.67 | Z91: =F91*Y91 -> 798.57754 | AA91: 872.76 | AB91: =F91*AA91 -> 799.57614
A92: 7 | B92: =VLOOKUP(C92,Universe!$C$2:$E$201,3,FALSE) -> Financials | C92: CB | D92: =VLOOKUP(C92,Universe!$C$2:$D$201,2,FALSE) -> Chubb Ltd | E92: 0.0666 | F92: =$D$85*E92/W92 -> 2.7827274 | W92: 280.51 | X92: =F92*W92 -> 780.58287 | Y92: 289.26 | Z92: =F92*Y92 -> 804.93174 | AA92: 274.7 | AB92: =F92*AA92 -> 764.41523
A93: 8 | B93: =VLOOKUP(C93,Universe!$C$2:$E$201,3,FALSE) -> Health Care | C93: VRTX | D93: =VLOOKUP(C93,Universe!$C$2:$D$201,2,FALSE) -> Vertex Pharma | E93: 0.0631 | F93: =$D$85*E93/W93 -> 1.4913817 | W93: 495.89 | X93: =F93*W93 -> 739.56125 | Y93: 469.79 | Z93: =F93*Y93 -> 700.63619 | AA93: 471.12 | AB93: =F93*AA93 -> 702.61973
A94: 9 | B94: =VLOOKUP(C94,Universe!$C$2:$E$201,3,FALSE) -> Health Care | C94: LLY | D94: =VLOOKUP(C94,Universe!$C$2:$D$201,2,FALSE) -> Eli Lilly and Company | E94: 0.048 | F94: =$D$85*E94/W94 -> 0.59135772 | W94: 951.34 | X94: =F94*W94 -> 562.58225 | Y94: 876.48 | Z94: =F94*Y94 -> 518.31321 | AA94: 811.52 | AB94: =F94*AA94 -> 479.89861
A95: 10 | B95: =VLOOKUP(C95,Universe!$C$2:$E$201,3,FALSE) -> Health Care | C95: UNH | D95: =VLOOKUP(C95,Universe!$C$2:$D$201,2,FALSE) -> UnitedHealth Group | E95: 0.0452 | F95: =$D$85*E95/W95 -> 0.92650265 | W95: 571.79 | X95: =F95*W95 -> 529.76495 | Y95: 567.11 | Z95: =F95*Y95 -> 525.42892 | AA95: 551.8 | AB95: =F95*AA95 -> 511.24416
A96: 11 | B96: =VLOOKUP(C96,Universe!$C$2:$E$201,3,FALSE) -> Financials | C96: PGR | D96: =VLOOKUP(C96,Universe!$C$2:$D$201,2,FALSE) -> Progressive Corp | E96: 0.033 | F96: =$D$85*E96/W96 -> 1.5655116 | W96: 247.06 | X96: =F96*W96 -> 386.7753 | Y96: 249.08 | Z96: =F96*Y96 -> 389.93763 | AA96: 237.86 | AB96: =F96*AA96 -> 372.37259
A97: 12 | B97: =VLOOKUP(C97,Universe!$C$2:$E$201,3,FALSE) -> Health Care | C97: BSX | D97: =VLOOKUP(C97,Universe!$C$2:$D$201,2,FALSE) -> Boston Scientific | E97: 0.0177 | F97: =$D$85*E97/W97 -> 2.5364006 | W97: 81.79 | X97: =F97*W97 -> 207.4522 | Y97: 84.14 | Z97: =F97*Y97 -> 213.41275 | AA97: 83.62 | AB97: =F97*AA97 -> 212.09382
X98: =SUM(X86:X97) -> 11720.464 | Z98: =SUM(Z86:Z97) -> 11947.281 | AB98: =SUM(AB86:AB97) -> 11701.669
Z99: =(Z98-X98)/X98 -> 0.019352291 | AB99: =(AB98-Z98)/Z98 -> -0.020558027
A101: ROUND 8 | D101: =AB98 -> 11701.669
A102: 1 | B102: =VLOOKUP(C102,Universe!$C$2:$E$201,3,FALSE) -> Information Technology | C102: TMUS | D102: =VLOOKUP(C102,Universe!$C$2:$D$201,2,FALSE) -> T-Mobile US | E102: 0.15 | F102: =$D$101*E102/AA102 -> 8.0126464 | AA102: 219.06 | AB102: =F102*AA102 -> 1755.2503 | AC102: 243.15 | AD102: =F102*AC102 -> 1948.275
A103: 2 | B103: =VLOOKUP(C103,Universe!$C$2:$E$201,3,FALSE) -> Utilities | C103: SO | D103: =VLOOKUP(C103,Universe!$C$2:$D$201,2,FALSE) -> Southern Company | E103: 0.15 | F103: =$D$101*E103/AA103 -> 20.657295 | AA103: 84.97 | AB103: =F103*AA103 -> 1755.2503 | AC103: 86.24 | AD103: =F103*AC103 -> 1781.4851
A104: 3 | B104: =VLOOKUP(C104,Universe!$C$2:$E$201,3,FALSE) -> Consumer Staples | C104: WMT | D104: =VLOOKUP(C104,Universe!$C$2:$D$201,2,FALSE) -> Walmart Inc. | E104: 0.15 | F104: =$D$101*E104/AA104 -> 21.6084 | AA104: 81.23 | AB104: =F104*AA104 -> 1755.2503 | AC104: 91.42 | AD104: =F104*AC104 -> 1975.4399
A105: 4 | B105: =VLOOKUP(C105,Universe!$C$2:$E$201,3,FALSE) -> Communication Services | C105: T | D105: =VLOOKUP(C105,Universe!$C$2:$D$201,2,FALSE) -> AT&T Inc. | E105: 0.125 | F105: =$D$101*E105/AA105 -> 69.093463 | AA105: 21.17 | AB105: =F105*AA105 -> 1462.7086 | AC105: 22.17 | AD105: =F105*AC105 -> 1531.8021
A106: 5 | B106: =VLOOKUP(C106,Universe!$C$2:$E$201,3,FALSE) -> Financials | C106: PGR | D106: =VLOOKUP(C106,Universe!$C$2:$D$201,2,FALSE) -> Progressive Corp | E106: 0.1131 | F106: =$D$101*E106/AA106 -> 5.564024 | AA106: 237.86 | AB106: =F106*AA106 -> 1323.4587 | AC106: 263.5 | AD106: =F106*AC106 -> 1466.1203
A107: 6 | B107: =VLOOKUP(C107,Universe!$C$2:$E$201,3,FALSE) -> Utilities | C107: NEE | D107: =VLOOKUP(C107,Universe!$C$2:$D$201,2,FALSE) -> NextEra Energy | E107: 0.1087 | F107: =$D$101*E107/AA107 -> 17.07115 | AA107: 74.51 | AB107: =F107*AA107 -> 1271.9714 | AC107: 76.29 | AD107: =F107*AC107 -> 1302.3581
...
